{
	"configurations" : 
	[
		{
			"abstractTargets" : [],
			"directories" : 
			[
				{
					"build" : ".",
					"jsonFile" : "directory-.-Debug-9ad1a58d4644cf6543fa.json",
					"minimumCMakeVersion" : 
					{
						"string" : "4.0"
					},
					"projectIndex" : 0,
					"source" : ".",
					"targetIndexes" : 
					[
						0
					]
				}
			],
			"name" : "Debug",
			"projects" : 
			[
				{
					"directoryIndexes" : 
					[
						0
					],
					"name" : "socialNetworkSim",
					"targetIndexes" : 
					[
						0
					]
				}
			],
			"targets" : 
			[
				{
					"directoryIndex" : 0,
					"id" : "socialNetworkSim::@6890427a1f51a3e7e1df",
					"jsonFile" : "target-socialNetworkSim-Debug-94e791d19f44ae9e2220.json",
					"name" : "socialNetworkSim",
					"projectIndex" : 0
				}
			]
		}
	],
	"kind" : "codemodel",
	"paths" : 
	{
		"build" : "/Users/ericpham/Documents/GitHub/SocialMediaProj/build",
		"source" : "/Users/ericpham/Documents/GitHub/SocialMediaProj"
	},
	"version" : 
	{
		"major" : 2,
		"minor" : 9
	}
}
